lima1983analysis/__init__.py
lima1983analysis/version.py
lima1983analysis_sebastian_achim_mueller-0.0.4.dist-info/LICENSE
lima1983analysis_sebastian_achim_mueller-0.0.4.dist-info/METADATA
lima1983analysis_sebastian_achim_mueller-0.0.4.dist-info/WHEEL
lima1983analysis_sebastian_achim_mueller-0.0.4.dist-info/top_level.txt
lima1983analysis_sebastian_achim_mueller-0.0.4.dist-info/RECORD
