Metadata-Version: 2.1
Name: lima1983analysis-sebastian-achim-mueller
Version: 0.0.4
Summary: Sensitivity, Ti-Pei Li and Yu-Qian-Ma, APJ 272:317-324, 1983
Home-page: https://github.com/cherenkov-plenoscope/lima1983analysis
Author: Sebastian Achim Mueller
Author-email: sebastian-achim.mueller@mpi-hd.mpg.de
Classifier: Programming Language :: Python :: 3
Classifier: License :: OSI Approved :: MIT License
Classifier: Operating System :: OS Independent
Classifier: Natural Language :: English
Classifier: Intended Audience :: Science/Research
License-File: LICENSE
